dbtesttools/__init__.py
dbtesttools/_version.py
dbtesttools/baseengine.py
dbtesttools/fixtures.py
dbtesttools/engines/__init__.py
dbtesttools/engines/postgres.py
dbtesttools/engines/sqlite.py
dbtesttools/tests/__init__.py
dbtesttools/tests/models.py
dbtesttools/tests/test_isolation.py
dbtesttools/tests/test_pgfixture.py
db_testtools-2025.5.6.dist-info/METADATA
db_testtools-2025.5.6.dist-info/WHEEL
db_testtools-2025.5.6.dist-info/licenses/AUTHORS
db_testtools-2025.5.6.dist-info/licenses/LICENCE.txt
db_testtools-2025.5.6.dist-info/RECORD
