Metadata-Version: 2.3
Name: db-testtools
Version: 2025.5.6
Project-URL: Source, https://github.com/juledwar/db-testtools
Author-email: Julian Edwards <juledwar@cisco.com>
Maintainer-email: Julian Edwards <juledwar@cisco.com>
Classifier: Development Status :: 5 - Production/Stable
Classifier: Environment :: Console
Classifier: Framework :: Hatch
Classifier: Intended Audience :: Developers
Classifier: Intended Audience :: Information Technology
Classifier: Natural Language :: English
Classifier: Operating System :: POSIX :: Linux
Classifier: Programming Language :: Python :: 3
Classifier: Programming Language :: Python :: 3.8
Classifier: Programming Language :: Python :: 3.9
Classifier: Programming Language :: Python :: 3.10
Classifier: Programming Language :: Python :: 3.11
Classifier: Programming Language :: Python :: 3.12
Classifier: Topic :: Utilities
Requires-Python: >=3.8
Requires-Dist: docker>=5.0.2
Requires-Dist: fixtures>=3.0.0
Requires-Dist: psycopg2-binary>=2.9.1
Requires-Dist: retry>=0.9.2
Requires-Dist: sqlalchemy>=1.4.23
Requires-Dist: testresources>=2.0.1
Provides-Extra: test
Requires-Dist: build>=0.7.0; extra == 'test'
Requires-Dist: coverage[toml]>=6.0.2; extra == 'test'
Requires-Dist: ipython>=7.28.0; extra == 'test'
Requires-Dist: pdbpp>=0.10.3; extra == 'test'
Requires-Dist: ruff>=0.5.3; extra == 'test'
Requires-Dist: sqlalchemy; extra == 'test'
Requires-Dist: stestr>=3.2.1; extra == 'test'
Requires-Dist: testresources; extra == 'test'
Requires-Dist: testscenarios>=0.5.0; extra == 'test'
Requires-Dist: testtools>=2.5.0; extra == 'test'
Requires-Dist: twine>=3.4.2; extra == 'test'
